{"TotalHands":1108,"HandsPlayed":257,"HandsWon":110,"Bank":3.14,"BankMin":-0.02,"BankMax":4.82,"RakePaid":1.955,"Name":"pokoslav2010","HandsLost":0,"TotalLostAmount":18.17,"TotalWinAmount":24.18,"ShoveAllInWin":3.58,"ShoveAllInLoss":0.00,"ShoveAllInWinCount":2,"ShoveAllInLostCount":0,"CallAllInWin":5.05,"CallAllInLoss":1.89,"CallAllInWinCount":7,"CallAllInLostCount":5,"PFRCount":96,"VPIPCount":236,"PostFlopRaiseCount":8,"PostFlopBetCount":135,"PostFlopCallCount":74,"WentToShowDownCount":74,"WentToShowDownAndWonCount":36,"FoldedToAllIn":18,"PlayersFirstFoundDate":"2021-02-19T00:00:00","CashOutGain":-0.33,"CallRaisedFirstIn":{"CallRaisedFirstInCounts":{"0.01":{"HoleCards":"A9,QT,33","RFIBet":0.01},"0.02":{"HoleCards":"A8s,QTs,QT,J9s,T8s,87","RFIBet":0.02},"0.04":{"HoleCards":"AJs,AJ,AT,QTs,QT,TT,88,65s","RFIBet":0.04},"0.05":{"HoleCards":"AJ","RFIBet":0.05},"0.06":{"HoleCards":"AK,AJ,ATs,AT,A6s,A5s,KQs,KJ,QJ","RFIBet":0.06},"0.07":{"HoleCards":"AJs,AJ","RFIBet":0.07},"0.08":{"HoleCards":"88","RFIBet":0.08},"0.10":{"HoleCards":"AK,KK,KTs,99","RFIBet":0.10},"0.30":{"HoleCards":"AQ,QQ","RFIBet":0.30},"0.50":{"HoleCards":"AA","RFIBet":0.50},"2":{"HoleCards":"AA","RFIBet":2.0}}},"RaisedFirstIn":{"RaisedFirstIn":{"0.01":{"HoleCards":"98","RFIBet":0.01},"0.02":{"HoleCards":"AT,A6s,A4s,A3s,A2s,KJ,Q8s,T9,76s","RFIBet":0.02},"0.06":{"HoleCards":"AQ,A9s,JTs","RFIBet":0.06},"0.08":{"HoleCards":"AA,AKs,AK,KK,JJ,TT","RFIBet":0.08}}},"HandMonitor":{"handMonitorCounts":{"AK":{"DealtCount":4,"HitCount":2,"FlopHitCount":1,"TurnHitCount":0,"RiverHitCount":1,"WonCount":3,"WonAmount":0.58,"LostCount":1,"LostAmount":1.52,"NotPlayedHitCount":0,"NotPlayedNotHitCount":0},"AA":{"DealtCount":4,"HitCount":0,"FlopHitCount":0,"TurnHitCount":0,"RiverHitCount":0,"WonCount":3,"WonAmount":4.89,"LostCount":1,"LostAmount":1.08,"NotPlayedHitCount":0,"NotPlayedNotHitCount":0},"KK":{"DealtCount":2,"HitCount":0,"FlopHitCount":0,"TurnHitCount":0,"RiverHitCount":0,"WonCount":2,"WonAmount":1.44,"LostCount":0,"LostAmount":0.0,"NotPlayedHitCount":0,"NotPlayedNotHitCount":0},"QQ":{"DealtCount":1,"HitCount":0,"FlopHitCount":0,"TurnHitCount":0,"RiverHitCount":0,"WonCount":0,"WonAmount":0.0,"LostCount":1,"LostAmount":-0.05,"NotPlayedHitCount":0,"NotPlayedNotHitCount":0},"JJ":{"DealtCount":1,"HitCount":0,"FlopHitCount":0,"TurnHitCount":0,"RiverHitCount":0,"WonCount":0,"WonAmount":0.0,"LostCount":1,"LostAmount":0.59,"NotPlayedHitCount":0,"NotPlayedNotHitCount":0},"TT":{"DealtCount":2,"HitCount":0,"FlopHitCount":0,"TurnHitCount":0,"RiverHitCount":0,"WonCount":1,"WonAmount":0.35,"LostCount":1,"LostAmount":0.54,"NotPlayedHitCount":0,"NotPlayedNotHitCount":0},"99":{"DealtCount":1,"HitCount":0,"FlopHitCount":0,"TurnHitCount":0,"RiverHitCount":0,"WonCount":1,"WonAmount":-0.09,"LostCount":0,"LostAmount":0.0,"NotPlayedHitCount":0,"NotPlayedNotHitCount":0},"88":{"DealtCount":2,"HitCount":1,"FlopHitCount":1,"TurnHitCount":0,"RiverHitCount":0,"WonCount":1,"WonAmount":1.87,"LostCount":1,"LostAmount":0.21,"NotPlayedHitCount":0,"NotPlayedNotHitCount":0},"77":{"DealtCount":0,"HitCount":0,"FlopHitCount":0,"TurnHitCount":0,"RiverHitCount":0,"WonCount":0,"WonAmount":0.0,"LostCount":0,"LostAmount":0.0,"NotPlayedHitCount":0,"NotPlayedNotHitCount":0},"66":{"DealtCount":0,"HitCount":0,"FlopHitCount":0,"TurnHitCount":0,"RiverHitCount":0,"WonCount":0,"WonAmount":0.0,"LostCount":0,"LostAmount":0.0,"NotPlayedHitCount":0,"NotPlayedNotHitCount":0},"55":{"DealtCount":0,"HitCount":0,"FlopHitCount":0,"TurnHitCount":0,"RiverHitCount":0,"WonCount":0,"WonAmount":0.0,"LostCount":0,"LostAmount":0.0,"NotPlayedHitCount":0,"NotPlayedNotHitCount":0},"44":{"DealtCount":0,"HitCount":0,"FlopHitCount":0,"TurnHitCount":0,"RiverHitCount":0,"WonCount":0,"WonAmount":0.0,"LostCount":0,"LostAmount":0.0,"NotPlayedHitCount":0,"NotPlayedNotHitCount":0},"33":{"DealtCount":1,"HitCount":0,"FlopHitCount":0,"TurnHitCount":0,"RiverHitCount":0,"WonCount":0,"WonAmount":0.0,"LostCount":1,"LostAmount":0.08,"NotPlayedHitCount":0,"NotPlayedNotHitCount":0},"22":{"DealtCount":0,"HitCount":0,"FlopHitCount":0,"TurnHitCount":0,"RiverHitCount":0,"WonCount":0,"WonAmount":0.0,"LostCount":0,"LostAmount":0.0,"NotPlayedHitCount":0,"NotPlayedNotHitCount":0}}},"BankByHand":{},"StartingHands":{"StartingHand":[[4,3,1,5,3,2,0,0,0,0,0,0,0],[1,2,0,4,0,0,0,0,0,0,0,0,0],[0,2,1,2,3,0,1,0,0,0,0,0,0],[2,0,0,1,0,0,1,0,0,0,0,0,0],[1,1,2,1,2,1,0,0,0,0,1,0,0],[1,0,0,1,0,1,1,0,0,0,0,0,0],[1,0,1,0,2,0,2,1,0,0,0,0,0],[0,0,0,0,0,0,0,0,0,0,0,0,0],[1,0,0,0,0,0,0,1,0,0,0,0,0],[1,0,0,0,0,0,0,0,1,0,0,0,0],[1,0,0,0,0,0,0,0,0,0,0,0,0],[1,0,0,0,0,0,0,0,0,0,0,1,0],[1,0,0,0,1,0,0,0,0,0,0,0,0]]},"StartingHandsByPosition":{"StartingHandByPosition":{"UTG":[[0,0,0,0,0,0,0,0,0,0,0,0,0],[0,1,0,0,0,0,0,0,0,0,0,0,0],[0,0,0,0,0,0,0,0,0,0,0,0,0],[0,0,0,1,0,0,0,0,0,0,0,0,0],[0,0,0,0,1,0,0,0,0,0,0,0,0],[0,0,0,0,0,0,0,0,0,0,0,0,0],[0,0,0,0,0,0,0,0,0,0,0,0,0],[0,0,0,0,0,0,0,0,0,0,0,0,0],[0,0,0,0,0,0,0,0,0,0,0,0,0],[0,0,0,0,0,0,0,0,0,0,0,0,0],[0,0,0,0,0,0,0,0,0,0,0,0,0],[0,0,0,0,0,0,0,0,0,0,0,0,0],[0,0,0,0,0,0,0,0,0,0,0,0,0]],"UTG1":[[0,0,0,0,0,0,0,0,0,0,0,0,0],[0,0,0,0,0,0,0,0,0,0,0,0,0],[0,0,0,0,0,0,0,0,0,0,0,0,0],[0,0,0,0,0,0,0,0,0,0,0,0,0],[0,0,0,0,0,0,0,0,0,0,0,0,0],[0,0,0,0,0,0,0,0,0,0,0,0,0],[0,0,0,0,0,0,0,0,0,0,0,0,0],[0,0,0,0,0,0,0,0,0,0,0,0,0],[0,0,0,0,0,0,0,0,0,0,0,0,0],[0,0,0,0,0,0,0,0,0,0,0,0,0],[1,0,0,0,0,0,0,0,0,0,0,0,0],[0,0,0,0,0,0,0,0,0,0,0,0,0],[0,0,0,0,0,0,0,0,0,0,0,0,0]],"UTG2":[[1,0,0,0,0,0,0,0,0,0,0,0,0],[0,0,0,1,0,0,0,0,0,0,0,0,0],[0,1,0,0,0,0,0,0,0,0,0,0,0],[0,0,0,0,0,0,0,0,0,0,0,0,0],[1,0,0,0,0,0,0,0,0,0,0,0,0],[0,0,0,0,0,0,0,0,0,0,0,0,0],[0,0,0,0,0,0,0,0,0,0,0,0,0],[0,0,0,0,0,0,0,0,0,0,0,0,0],[0,0,0,0,0,0,0,0,0,0,0,0,0],[0,0,0,0,0,0,0,0,0,0,0,0,0],[0,0,0,0,0,0,0,0,0,0,0,0,0],[0,0,0,0,0,0,0,0,0,0,0,0,0],[0,0,0,0,0,0,0,0,0,0,0,0,0]],"LJ":[[1,1,0,0,1,0,0,0,0,0,0,0,0],[0,0,0,0,0,0,0,0,0,0,0,0,0],[0,0,0,0,0,0,0,0,0,0,0,0,0],[0,0,0,0,0,0,0,0,0,0,0,0,0],[0,0,0,1,0,1,0,0,0,0,0,0,0],[0,0,0,0,0,0,0,0,0,0,0,0,0],[0,0,0,0,0,0,0,0,0,0,0,0,0],[0,0,0,0,0,0,0,0,0,0,0,0,0],[0,0,0,0,0,0,0,1,0,0,0,0,0],[0,0,0,0,0,0,0,0,0,0,0,0,0],[0,0,0,0,0,0,0,0,0,0,0,0,0],[0,0,0,0,0,0,0,0,0,0,0,0,0],[1,0,0,0,0,0,0,0,0,0,0,0,0]],"HJ":[[0,1,1,1,0,0,0,0,0,0,0,0,0],[0,0,0,1,0,0,0,0,0,0,0,0,0],[0,0,0,1,0,0,0,0,0,0,0,0,0],[0,0,0,0,0,0,0,0,0,0,0,0,0],[0,1,1,0,0,0,0,0,0,0,0,0,0],[1,0,0,0,0,0,0,0,0,0,0,0,0],[0,0,0,0,1,0,0,0,0,0,0,0,0],[0,0,0,0,0,0,0,0,0,0,0,0,0],[1,0,0,0,0,0,0,0,0,0,0,0,0],[0,0,0,0,0,0,0,0,1,0,0,0,0],[0,0,0,0,0,0,0,0,0,0,0,0,0],[1,0,0,0,0,0,0,0,0,0,0,0,0],[0,0,0,0,0,0,0,0,0,0,0,0,0]],"CO":[[1,1,0,0,0,0,0,0,0,0,0,0,0],[0,0,0,0,0,0,0,0,0,0,0,0,0],[0,1,0,1,0,0,0,0,0,0,0,0,0],[0,0,0,0,0,0,0,0,0,0,0,0,0],[0,0,0,0,0,0,0,0,0,0,0,0,0],[0,0,0,0,0,0,0,0,0,0,0,0,0],[0,0,0,0,0,0,1,0,0,0,0,0,0],[0,0,0,0,0,0,0,0,0,0,0,0,0],[0,0,0,0,0,0,0,0,0,0,0,0,0],[1,0,0,0,0,0,0,0,0,0,0,0,0],[0,0,0,0,0,0,0,0,0,0,0,0,0],[0,0,0,0,0,0,0,0,0,0,0,0,0],[0,0,0,0,0,0,0,0,0,0,0,0,0]],"Button":[[0,0,0,2,0,0,0,0,0,0,0,0,0],[1,0,0,1,0,0,0,0,0,0,0,0,0],[0,0,1,0,1,0,0,0,0,0,0,0,0],[0,0,0,0,0,0,0,0,0,0,0,0,0],[0,0,1,0,0,0,0,0,0,0,0,0,0],[0,0,0,1,0,1,0,0,0,0,0,0,0],[0,0,1,0,0,0,0,1,0,0,0,0,0],[0,0,0,0,0,0,0,0,0,0,0,0,0],[0,0,0,0,0,0,0,0,0,0,0,0,0],[0,0,0,0,0,0,0,0,0,0,0,0,0],[0,0,0,0,0,0,0,0,0,0,0,0,0],[0,0,0,0,0,0,0,0,0,0,0,0,0],[0,0,0,0,0,0,0,0,0,0,0,0,0]],"SB":[[0,0,0,1,1,2,0,0,0,0,0,0,0],[0,1,0,0,0,0,0,0,0,0,0,0,0],[0,0,0,0,2,0,0,0,0,0,0,0,0],[1,0,0,0,0,0,0,0,0,0,0,0,0],[0,0,0,0,0,0,0,0,0,0,0,0,0],[0,0,0,0,0,0,1,0,0,0,0,0,0],[0,0,0,0,0,0,0,0,0,0,0,0,0],[0,0,0,0,0,0,0,0,0,0,0,0,0],[0,0,0,0,0,0,0,0,0,0,0,0,0],[0,0,0,0,0,0,0,0,0,0,0,0,0],[0,0,0,0,0,0,0,0,0,0,0,0,0],[0,0,0,0,0,0,0,0,0,0,0,1,0],[0,0,0,0,0,0,0,0,0,0,0,0,0]],"BB":[[1,0,0,1,1,0,0,0,0,0,0,0,0],[0,0,0,1,0,0,0,0,0,0,0,0,0],[0,0,0,0,0,0,1,0,0,0,0,0,0],[1,0,0,0,0,0,1,0,0,0,0,0,0],[0,0,0,0,1,0,0,0,0,0,1,0,0],[0,0,0,0,0,0,0,0,0,0,0,0,0],[1,0,0,0,1,0,1,0,0,0,0,0,0],[0,0,0,0,0,0,0,0,0,0,0,0,0],[0,0,0,0,0,0,0,0,0,0,0,0,0],[0,0,0,0,0,0,0,0,0,0,0,0,0],[0,0,0,0,0,0,0,0,0,0,0,0,0],[0,0,0,0,0,0,0,0,0,0,0,0,0],[0,0,0,0,1,0,0,0,0,0,0,0,0]]}},"BankNetByHand":{"0":0.0,"223993977060":-0.02,"223994003732":1.07,"223994059093":-0.28,"223994088805":0.0,"223994125844":0.0,"223994137607":0.0,"223994145613":0.0,"223994171066":0.0,"223994184968":0.0,"223994208929":-0.06,"223994245448":-0.01,"223994264123":0.0,"223994287432":0.15,"223994337707":-0.02,"223994380416":0.0,"223994411791":0.0,"223994442426":0.0,"223994470676":-0.02,"223994483327":-0.01,"223994543486":0.0,"223994572636":0.0,"223994594561":0.0,"223994612827":-0.06,"223994654093":0.0,"223994660438":0.0,"223994675406":-0.02,"223994709782":-0.01,"223994738034":0.0,"223994768208":0.0,"223994782412":0.0,"223994802191":0.21,"223994847330":0.0,"223994874054":0.0,"223994894492":-0.02,"224471755374":-0.02,"224471762631":-0.01,"224471771567":0.0,"224471778092":0.0,"224471785421":0.0,"224471793158":0.0,"224471807265":0.0,"224471814545":0.0,"224471821749":-0.02,"224471828739":-0.01,"224471834309":-0.08,"224471845283":0.51,"224471855988":0.0,"224471861891":0.0,"224471868054":0.0,"224471873582":0.0,"224471881936":0.0,"224471885318":-0.02,"224471890643":-0.01,"224471893687":0.0,"224682437271":-0.02,"224682444152":-0.14,"224682452730":0.0,"224682456810":0.03,"224682462512":0.0,"224682467393":0.0,"224682472355":0.0,"224682477315":-0.02,"224682481225":-0.01,"224682485503":0.0,"224682489059":0.0,"224682500786":0.0,"224682503530":0.19,"224682512762":0.0,"224957166232":-0.02,"224957172646":-0.01,"224957178309":0.0,"224957184934":0.0,"224957190770":0.0,"224957196906":0.0,"224957204248":0.0,"224957215463":0.0,"224957221987":-0.02,"224957225136":-0.16,"224957232522":0.0,"224957240423":0.0,"224957247325":0.0,"224957254769":0.0,"224957273639":0.0,"224957280546":0.0,"224957286878":1.68,"224957298708":-0.01,"224957307832":0.0,"224957329745":0.0,"224957336857":0.03,"224957342552":0.0,"224957354642":0.0,"224957368747":0.0,"224957372855":0.05,"224957380359":0.13,"224957388998":0.0,"224957405234":-0.06,"224957413044":0.0,"224957422256":-0.16,"224957436535":0.0,"224957448486":0.0,"224957456955":0.0,"224957466740":0.05,"224957476713":-0.01,"224957494207":0.0,"224957505836":-0.21,"224957517719":0.0,"224957530656":0.0,"224957543220":0.0,"224957556158":0.0,"224957565785":-0.02,"224957573267":-0.01,"224957580476":-0.08,"224957593522":0.0,"224957606027":0.0,"224957610433":0.0,"224957622012":0.0,"224957627977":-0.02,"224957640888":-0.01,"224957644804":0.0,"224957658123":0.0,"224957664800":0.0,"224957668562":-0.02,"224957679747":0.0,"224957685345":0.03,"224957688885":0.0,"224957696591":0.15,"224957707122":-0.01,"224957710315":0.0,"224957715022":0.03,"224957720935":0.0,"224957728529":0.08,"224957734559":0.0,"224957738118":0.0,"224957743744":-0.02,"224957751242":-0.01,"224957776598":0.0,"224957781238":0.07,"224957785686":-0.02,"224957794112":-0.01,"224957800796":-0.09,"224957810774":0.0,"224957817411":0.0,"224957827039":-0.41,"224957841900":0.0,"224957858989":0.0,"224957865092":0.0,"224957871531":0.07,"224957879036":-0.35,"224957891727":0.0,"224957904257":-0.08,"224957919673":0.0,"224957928364":0.0,"224957936355":0.0,"224957948876":-0.02,"224957963585":0.33,"224957975151":-0.20,"224957989071":0.0,"224957999229":0.03,"224958002492":-0.10,"224958016970":0.0,"224958021657":-0.02,"224958033255":-0.02,"224958043056":0.0,"224958051660":0.0,"224958072045":0.0,"224958080515":0.0,"224958091003":0.0,"224958100477":0.0,"225080316341":0.0,"225080352322":-0.02,"225080389142":-0.27,"225080409392":0.0,"225080439268":0.0,"225080448702":0.0,"225080470099":0.0,"225080494915":0.0,"225080527231":-0.02,"225080554844":-0.01,"225080590626":0.0,"225080602556":0.0,"225080645230":0.03,"225080657297":0.81,"225080698417":0.0,"225080779695":0.0,"225080815972":0.31,"225080840188":-0.01,"225080893148":0.0,"225080945045":0.0,"225080960178":0.0,"225081006994":0.0,"225081041491":-0.03,"225081079966":0.0,"225081092041":0.0,"225081110758":-0.02,"225081118603":-0.01,"225081140172":0.0,"225081272729":0.0,"225081296140":0.0,"225081328551":-0.02,"225081368686":-0.01,"225081377173":0.10,"225081416426":0.0,"225081434603":-0.08,"225081461972":0.0,"225081497913":0.0,"225081530739":0.0,"225081538320":-0.06,"225081571944":-0.01,"225081589028":0.0,"225081597417":0.0,"225081666543":0.0,"225415647754":0.0,"225415658463":-0.02,"225415667606":-0.08,"225415673872":-0.02,"225415680555":0.0,"225415692644":0.0,"225415704527":-0.02,"225415716352":-0.06,"225415729421":1.01,"225415746430":-0.02,"225415763965":-0.02,"225415770986":0.0,"225415776389":0.0,"225415783927":0.0,"225415785926":0.0,"225415792176":0.0,"225415802091":0.0,"225415811158":0.0,"225415816918":-0.02,"225415823197":-0.01,"225415831494":0.0,"225415843255":0.0,"225415848301":0.0,"225415851275":0.0,"225415854778":0.0,"225415862928":0.0,"225415874598":-0.02,"225415889223":-0.01,"225415894146":0.0,"225415897638":0.0,"225415912346":0.0,"225415915262":-0.06,"225415931000":0.0,"225415943398":-0.02,"225415954240":0.0,"225415963012":-0.02,"225415970814":-0.01,"225415984572":-0.04,"225415994064":0.0,"225415997905":-0.02,"225416009011":-0.08,"225416015397":0.0,"225416024334":0.0,"225416031780":0.0,"225416037746":-0.02,"225416050177":-0.01,"225416054731":0.03,"225416061984":0.0,"225416070254":-0.02,"225416082047":0.0,"225416098621":0.0,"225416111845":0.01,"225416114825":-0.01,"225416118125":0.05,"225416129313":0.0,"225416133734":-0.02,"225416141905":0.0,"225416151016":0.0,"225416168006":0.01,"225416171096":-0.01,"225416174599":0.0,"225416186217":0.0,"225416189848":0.0,"225416201352":-0.13,"225416213971":0.0,"225416219990":0.0,"225416230040":-0.02,"225416236272":0.15,"225416244412":0.09,"225416255146":0.0,"225416259053":-0.09,"225416268407":0.0,"225416278543":0.0,"225416285642":0.0,"225416290339":0.03,"225416298253":-0.01,"225416304608":0.0,"225416322226":-0.06,"225416329728":0.0,"225416340024":0.0,"225416350622":0.0,"225416355548":0.01,"225416357797":-0.01,"225416370510":-0.06,"225416383551":0.0,"225416390789":0.95,"225416406030":0.0,"225416428231":0.0,"225416446990":0.10,"225416455169":0.0,"226596522976":-0.12,"226596532180":-0.01,"226596537487":0.0,"226596542003":0.0,"226596548405":0.0,"226596553441":0.0,"226596559899":0.0,"226596567794":0.0,"226596572628":-0.02,"226596591928":-0.01,"226596598164":-0.01,"226596609239":0.0,"226596624292":0.0,"226596634806":0.0,"226596647279":0.0,"226596653139":-0.02,"226596664178":0.0,"226596667482":0.02,"226596680344":-0.07,"226596690463":0.02,"226596705301":0.0,"226596717262":0.0,"226596726959":-0.02,"226596733127":-0.06,"226596742563":-0.04,"226596755700":-0.55,"226596762384":0.40,"226596769987":0.0,"226596776851":0.0,"226596780622":-0.09,"226596803719":-0.02,"226596810901":-0.06,"226596824774":0.0,"226596834255":0.0,"226596838198":0.0,"226596849450":0.10,"226596855951":0.0,"226596862363":0.0,"226596881493":0.0,"226596887935":-0.07,"226596901814":-0.01,"226596904378":0.0,"226596907599":0.0,"226596922189":-0.06,"226596928793":0.0,"226596934291":0.05,"226596939453":0.0,"226596950558":0.0,"226596953946":-0.02,"226596957517":-0.01,"226596964281":0.0,"226596969013":0.0,"226596976363":0.0,"226596982199":0.0,"226596990440":0.0,"226596999290":0.0,"226597005912":0.0,"226974566940":-0.02,"226974586065":-0.01,"226974620101":0.0,"226974638167":0.0,"226974658768":-0.06,"226974690387":0.0,"226974711039":0.0,"226974743400":0.0,"226974765037":-0.02,"226974807289":-0.02,"226974848813":-0.01,"226974863139":0.0,"226974897798":0.0,"226974954234":-1.52,"226974991379":0.0,"226975001022":-0.14,"226975022357":0.0,"227221444006":0.0,"227221449675":0.0,"227221457501":-0.02,"227221488991":0.03,"227221505206":0.0,"227221530508":0.0,"227221542331":-0.02,"227221562876":-0.01,"227221586371":0.05,"227221605156":0.0,"227221710993":0.07,"227221741291":-0.01,"227221757933":-0.06,"227221767318":0.0,"227221784926":0.0,"227221795949":0.0,"227221805375":0.0,"227221815924":0.0,"227221825853":0.03,"227221832459":-0.01,"227221843588":0.0,"227221853175":0.0,"227221856884":0.0,"227221870622":0.0,"227221884886":0.0,"227221893408":-0.02,"227221898852":0.04,"227221906868":0.0,"227221917154":0.0,"227221934773":0.0,"227221945272":0.03,"227221952407":0.21,"227221974286":-0.01,"227221986314":0.0,"227221994093":-0.16,"227222012503":0.0,"227222019935":0.0,"227222030922":0.0,"227222046979":-0.05,"227222066788":-0.01,"227222077216":0.0,"227222090953":0.0,"227222103255":0.09,"227222116123":0.0,"227222134716":0.0,"227222156322":-0.02,"227222176832":-0.01,"227222187804":0.07,"227222196103":0.0,"227222219971":0.0,"227222231885":0.0,"227222254385":-0.06,"227222281250":0.0,"227222297448":-0.02,"227222305951":-0.01,"227222326210":0.0,"227222342783":0.0,"227222356928":-0.06,"227222381605":0.08,"227222393992":0.0,"227222405388":0.0,"227222421463":0.0,"227222441143":-0.02,"227222453227":-0.01,"227222468852":0.0,"227222477327":0.0,"227222486035":0.0,"227222501117":0.0,"227222520639":0.0,"227222534506":0.0,"227222572295":-0.08,"227222598088":-0.01,"227222624249":0.0,"227222629252":0.0,"227222646656":0.0,"227222664119":0.0,"227222680028":0.0,"227222694450":0.0,"227222708028":-0.02,"227222721435":-0.01,"227222736254":0.0,"227222754684":0.0,"227222763991":0.0,"227222774864":0.0,"227222789818":0.0,"227222798732":0.0,"227222830027":0.0,"227222850958":-0.02,"227222860035":-0.01,"227222877588":0.0,"227222909789":0.0,"227222928781":-0.02,"227222941649":0.0,"227222958350":0.0,"227222988389":0.0,"227223011185":1.87,"227223079473":0.0,"227223092434":0.0,"227365522886":-0.02,"227365529098":-0.01,"227365535272":-0.24,"227365552884":0.0,"227365561324":-0.75,"227365575195":-0.02,"227365579052":0.0,"227365599716":-0.02,"227365607167":0.0,"227365614355":0.05,"227365618562":0.0,"227365624169":0.0,"227365634222":0.0,"227365641470":-0.02,"227365649123":0.02,"227365656150":0.30,"227365664582":0.0,"227365675546":0.0,"227365680638":0.08,"227365693315":0.0,"227365697200":-0.02,"227365702675":-0.01,"227365706564":0.0,"227365721083":0.0,"227365723968":0.0,"227365731113":0.0,"227365742521":0.09,"227365760030":0.0,"227365763492":-0.02,"227365773519":-0.01,"227365777307":-0.02,"227365802591":0.0,"227365806793":0.0,"227365822317":0.0,"227365831667":0.0,"227365838850":0.0,"227365845009":-0.02,"227365850341":0.09,"227365879300":0.0,"227365885837":0.0,"227365889843":0.0,"227365893697":0.0,"227365898714":0.08,"227365908616":0.11,"227365915026":-0.02,"227365920520":0.03,"227365924324":-0.18,"227365939868":0.0,"227365946316":0.0,"227365953479":0.0,"227365962330":0.0,"227365964734":-0.02,"227365973145":-0.01,"227365976314":0.0,"227365979569":0.0,"227365987183":0.03,"227365993319":0.0,"227365999913":0.0,"227366004336":0.20,"227366013612":-0.02,"227366023245":-0.01,"227366029045":0.0,"227366033828":0.0,"227366043831":0.0,"227366054038":0.0,"227366056240":0.0,"227366063975":0.0,"227366068044":-0.02,"227366070665":-0.01,"227366074177":0.0,"227366076949":0.0,"227366083693":0.0,"227366094294":-0.08,"227366105771":-0.27,"227366119296":-0.06,"227366125974":-0.01,"227366132987":0.0,"227366140717":0.0,"227366146369":0.0,"227366150792":0.0,"227366157702":0.0,"227366168437":0.0,"227366181633":-0.02,"227366186833":-0.01,"227366194799":0.0,"227366199139":0.0,"227366219013":-0.06,"227366239268":0.0,"227366257039":0.0,"227366259092":0.35,"227366274096":-0.02,"227366279240":-0.01,"227366287710":0.0,"227366290894":0.0,"227366298488":-0.76,"227366327439":0.0,"227366341496":0.0,"227366355570":-0.02,"227366369613":-0.18,"227366378945":0.0,"227366383051":-0.08,"227366408782":0.0,"227366414769":0.0,"227366433867":0.0,"227366443976":-0.02,"227366458068":0.0,"227366464374":-0.02,"227366482551":-0.06,"227366497883":0.40,"227366518760":0.0,"227366537340":0.0,"227366541801":0.05,"227366546100":0.0,"227366553202":0.0,"227366567433":-0.02,"227366578719":-0.01,"227366587178":0.0,"227366593668":0.0,"227366600189":0.0,"227366610630":0.0,"227366623276":0.0,"227366627686":-0.06,"227366652969":-0.18,"227366663202":-0.01,"227366665959":0.08,"227366675403":0.0,"227366685206":0.0,"227366696137":0.0,"227366704051":0.0,"227366727530":-0.06,"227366740681":-0.01,"227366743799":0.0,"227366750418":0.0,"227366760224":0.0,"227366763742":0.04,"227366771014":0.0,"227366783557":0.0,"227366795044":0.0,"227366800357":-0.02,"227366803951":-0.01,"227366821049":0.0,"227366827664":0.0,"227366832358":0.0,"227366838261":-0.19,"227366857288":0.0,"227366868821":0.0,"227366876879":0.0,"228172206656":-0.12,"228172231095":-0.01,"228172257101":-0.44,"228172294086":0.0,"228172307844":0.0,"228172335774":0.51,"228172367404":-0.12,"228172430288":0.0,"228172456878":0.0,"228172475863":-0.02,"228172522528":-0.02,"228172543201":0.0,"228172574368":0.0,"228172604931":0.0,"228172626495":0.0,"228172664580":0.0,"228172691857":0.0,"228172731564":0.0,"228172743070":1.78,"228172774202":-0.01,"228172796263":0.18,"228172820355":1.31,"228172843691":0.0,"228172866032":0.0,"228172876414":0.03,"228243668986":0.05,"228243678890":-0.02,"228243691972":-0.01,"228243708927":0.0,"228243723241":0.0,"228243729217":0.0,"228243750104":0.03,"228243787060":0.0,"228243811176":-0.02,"228243841495":-0.01,"228243862662":0.0,"228243871009":0.0,"228243886974":0.0,"228243893618":0.0,"228243902467":0.0,"228243918570":-0.01,"228243928718":0.0,"228243936496":0.0,"228243944706":0.0,"228243995905":-0.01,"228244015575":0.0,"228244035237":0.0,"228244063317":0.0,"228244085073":0.0,"228244098075":0.0,"228244130107":0.0,"228244164423":0.0,"228244187343":-0.06,"228244199736":-0.01,"228244210508":0.0,"228244220216":0.0,"228244229553":0.0,"228244244194":0.24,"228244266259":0.0,"228244293182":0.0,"228244303363":0.05,"228244340957":-0.01,"228244359127":0.0,"228244410422":-0.08,"228244439156":0.0,"228244451139":0.0,"228244480173":-1.08,"229951129896":0.03,"229951145404":-0.98,"229951168779":0.0,"229951185636":-0.02,"229951195644":0.0,"229951234954":0.0,"229951263186":-0.59,"229951286292":-0.02,"229951297803":-0.19,"229951329709":0.0,"229951346168":0.0,"229951362408":-0.23,"230491470729":-0.02,"230491474038":-0.01,"230491479853":0.0,"230491487499":-0.04,"230491495587":0.14,"230491502824":-0.02,"230491507362":0.0,"230491511110":0.0,"230491515572":0.0,"230491518396":0.07,"230491526306":-0.01,"230491530064":0.0,"230491544351":0.0,"230491555859":0.0,"230491562060":0.0,"230491569810":0.0,"230491583219":0.0,"230491594203":-0.02,"230491612596":0.26,"230491621535":0.0,"230491627678":0.0,"230491631784":0.0,"230491636586":0.0,"230491643872":0.0,"230491652258":0.12,"230491656644":0.06,"230491661890":0.0,"230491664467":0.0,"230491673175":0.0,"230491680209":0.03,"230491683605":0.0,"230491688216":-0.02,"230491696803":-0.01,"230491701286":0.0,"230491712143":0.0,"230491715728":0.03,"230491720134":0.0,"230491725296":0.0,"230491731300":0.0,"230491733314":-0.02,"230491736747":-0.01,"230491741190":0.0,"230491745991":0.0,"230491754836":0.0,"230491756922":0.0,"230491762447":-0.02,"230491764597":-0.01,"230491769297":-0.05,"230491776359":-0.02,"230491781481":0.0,"230491784850":0.0,"230491786947":0.0,"230491795331":0.0,"230491800838":-0.38,"230491823727":0.08,"230491830845":-0.01,"230491833828":0.0,"230491836496":0.0,"230491840742":-0.08,"230491851343":0.0,"230491855055":0.0,"230491856833":0.0,"230491860423":-0.02,"230491864431":0.13,"230491870766":-0.18,"230491877046":0.0,"230491892304":-0.06,"230491900289":0.0,"230491904502":0.0,"230491915449":0.0,"230491926454":0.0,"230491933210":-0.02,"230491939086":-0.01,"230491942889":-0.06,"230491950485":0.0,"230491961831":0.0,"230491966044":0.0,"230491970126":0.0,"230491973348":0.0,"230491981679":0.0,"230491989409":-0.02,"230491996543":-0.01,"230492005536":0.08,"230492011163":0.0,"230492014347":0.0,"230492022204":0.0,"230492027427":0.0,"230492035707":0.0,"230492038743":0.0,"230492046611":-0.02,"230492055760":-0.01,"230492063213":0.0,"230492066718":0.0,"230492073895":0.0,"230492080607":0.0,"230492085196":0.0,"230492088838":0.0,"230492092695":0.0,"230492096948":0.27,"230492105966":-0.01,"230492113514":-0.02,"230492119323":-0.06,"230492127877":-0.10,"230492138450":-0.02,"230492144813":0.0,"230492148437":0.0,"230492156484":0.0,"230492608155":0.0,"230492612545":0.0,"230492624839":0.0,"230492645823":0.0,"230492648959":0.0,"230492656639":0.0,"230492666190":-0.02,"230492671832":-0.01,"230492684099":-0.02,"230492693541":0.0,"230492702869":0.0,"230492717521":0.0,"230492725481":0.0,"230492734484":0.03,"230492738439":-0.05,"230492746963":-0.23,"230492756028":-0.05,"230492778685":0.0,"230492789313":0.0,"230492800730":0.0,"230492811587":0.0,"230492816177":0.0,"230492827607":0.0,"230492837127":-0.02,"230492840851":-0.01,"230492844941":0.07,"230492850735":1.27,"230492867608":0.0,"230492876587":0.0,"230492880540":0.0,"231320526188":0.0,"231320571742":0.0,"231320584147":0.0,"231320643922":0.0,"231320694546":-0.02,"231320734435":-0.01,"231320757603":0.0,"231320802822":0.0,"231320838244":0.0,"231320870389":0.0,"231320881151":0.0,"231320902408":-0.06,"231320927275":-0.06,"231320979732":-0.04,"231321020887":-0.08,"231321044525":0.0,"231321069346":0.0,"231321100643":0.0,"231321138302":-0.06,"231321178361":0.0,"231321212730":0.0,"231321234709":-0.25,"231321261338":-0.02,"231321311978":-0.01,"231321319246":0.0,"231321344971":0.0,"231321373262":0.0,"231321409482":0.0,"231321415495":-0.04,"231321440156":0.0,"231321640377":-0.02,"231321684984":-0.02,"231321712619":0.0,"231321748706":-0.08,"231321794273":0.0,"231321803452":-0.06,"231321824878":0.0,"231321843469":0.0,"231321863527":0.01,"231321870283":0.74,"231321912564":-0.04,"231321970583":0.0,"231321997969":0.0,"231322005450":0.0,"231322031157":0.0,"231322064335":0.0,"231322082326":0.0,"231322107138":-0.04,"231322133871":-0.01,"231322152784":0.0,"231322163835":0.0,"231322193730":0.0,"231322227142":0.0,"231322254354":0.0,"231322297989":0.0,"231322312094":0.0,"231322350216":0.00,"231322380064":-0.01,"231322402282":-0.11,"231322430048":0.0,"231322458297":0.0,"231322468701":0.0,"231322485077":0.0,"231322519619":0.0,"232476045508":-0.01,"232476049708":0.0,"232476057801":0.03,"232476063616":0.0,"232476067765":0.0,"232476072289":0.0,"232476075953":-0.02,"232476080240":-0.01,"232476080620":0.0,"232476089786":0.0,"232476090744":-0.02,"232476097105":-0.01,"232476097315":0.0,"232476101406":0.0,"232476106997":-0.02,"232476107062":-0.06,"232476115345":1.80,"232476119770":-0.02,"232476127857":0.0,"232476129899":0.0,"232476130246":-0.02,"232476134524":-0.02,"232476137420":-0.01,"232476139455":0.0,"232476142870":0.0,"232476148268":0.0,"232476165126":0.03,"232476174389":0.0,"232476176878":0.0,"232476222515":0.09,"232476227042":-0.04,"232476233419":-0.01,"232476235741":-0.01,"232476236517":0.0,"232476239821":0.0,"232476251335":0.0,"232476258838":0.0,"232476261916":0.0,"232476266519":0.0,"232476269639":-0.54,"232476270727":0.0,"232476278363":0.04,"232476279114":-0.01,"232476284562":0.0,"232476286580":-0.01,"232476290679":-0.06,"232476293105":0.0,"232476296548":0.0,"232476297701":0.0,"232476303190":0.0,"232476306217":0.0,"232476308905":0.0,"232476309034":0.0,"232476311973":-0.02,"232476315059":-0.01,"232476318888":0.0,"232476318955":0.0,"232476323252":0.0,"232476324145":0.0,"232476327841":0.0,"232476330763":-0.08,"232476333472":-0.06,"232476337542":-0.01,"232476344041":0.47,"232476346232":0.0,"232476354333":0.0,"232476354928":0.0,"232476359843":0.0,"232476360630":0.0,"232476364852":0.24,"232476368148":0.01,"232476370676":-0.01,"232476375305":0.0,"232476376823":0.0,"232476382580":0.0,"232476385659":0.0,"232476389963":-0.02,"232476390553":0.0,"232476397609":0.0,"232476398916":-0.01,"232476401886":-0.08,"232476403713":0.12,"232476409036":-0.13,"232476410519":0.0,"232476415743":0.0,"232476419513":0.0,"232476422433":-0.02,"232476425315":0.0,"232476425345":-0.01,"232476434136":0.0,"232476435199":0.0,"232476440595":0.0,"232476445996":0.0,"232476447329":-0.02,"232476454392":-0.16,"232476455295":0.0,"232476462941":0.03,"232476468852":0.0,"232476470291":0.0,"232476476189":0.0,"232476477151":0.0,"232476478892":-0.02,"232476480173":0.0,"232476481963":-0.01,"232476487980":0.0,"232476489753":0.0,"232476491281":-0.02,"232476496614":0.0,"232476499120":0.0,"232476502081":0.0,"232476502103":-0.04,"232476505722":0.0,"232476507455":0.0,"232476509605":0.0,"232476515144":-0.02,"232476516831":-0.02,"232476520278":-0.01,"232476521328":-0.01,"232476521725":0.0,"232476527088":0.0,"232476527230":0.0,"232476533369":0.0,"232476537072":-0.04,"232476541136":0.0,"232476545797":0.0,"232476547945":0.0,"232476552319":0.0,"232476554520":0.0,"232476557351":-0.06,"232476558371":0.0,"232476561714":-0.08,"232476568434":0.0,"232476569393":0.0,"232476571715":-0.02,"232476573572":0.0,"232476576336":0.0,"232476579642":0.0,"232476582342":0.0,"232476588354":0.0,"232476593156":0.06,"232476604280":-0.01,"232476608319":0.0,"232476617533":0.0,"232476621433":0.0,"232476628139":-0.02,"232476632168":-0.01,"232476634482":0.0,"232476642129":-0.02,"232476642899":-0.10,"232476650690":-0.08,"232476656506":0.0,"232476664790":0.0,"232476666854":0.0,"232476669781":0.0,"232476687846":0.0,"232476689097":0.0,"232476694099":0.0,"232476694568":-0.02,"232476699475":-0.01,"232476702874":0.0,"232476705380":0.0,"232476709474":-0.02,"232476709498":0.0,"232476715043":0.43,"232476719417":0.0,"232476723985":0.0,"232476729394":0.0,"232476732713":0.0,"232476739840":0.0,"232476740749":0.0,"232476746403":0.31,"232476749061":0.0,"232476755650":0.0,"232476755918":-0.02,"232476758675":0.0,"232476761377":-0.01,"232476763620":0.0,"232476764774":0.12,"232476767415":0.0,"232476772638":-0.02,"232476777227":0.0,"232476780261":-0.01,"232476782523":-0.06,"232476789580":0.0,"232476792278":0.0,"232476796043":0.0,"232476801846":0.0,"232476802591":0.0,"232476808913":0.0,"232476811794":-0.02,"232476817860":-0.01,"232476830058":0.0,"232476837293":0.0,"232476843834":0.0,"232653543976":-0.02,"232653551312":-0.16,"232653560904":0.0,"232653572620":-0.02,"232653591132":0.0,"232653601242":0.0,"232653610431":0.0,"232653621363":0.0,"232653635343":-0.02,"232653710145":-0.06,"232653724925":-0.24,"232653732284":-0.01,"232653739803":0.0,"232653745613":0.0},"PositionPlayedCount":{"UTG":17,"UTG1":7,"UTG2":17,"LJ":35,"HJ":36,"CO":28,"Button":38,"SB":33,"BB":39},"WinByPositionPlayedCount":{"UTG":9,"UTG1":2,"UTG2":8,"LJ":18,"HJ":11,"CO":8,"Button":15,"SB":12,"BB":27},"Steal":{"FoldedToSteal":46,"TotalStolen":1.09,"wonAmount":{"CO":0.59,"Button":0.19,"SB":0.32},"lostAmount":{"CO":-0.06,"Button":-0.11,"SB":-0.38},"stealPosition":{"CO":5,"Button":5,"SB":5},"unsuccessfulStealPosition":{"CO":3,"Button":4,"SB":5}},"AllIns":{"TotalAllInCount":14,"allInCounts":{"AA":{"DealtCount":4,"WonCount":1,"WonAmount":1.31,"ShoveWonCount":2,"ShoveWonAmount":3.58,"ShoveLostCount":0,"ShoveLostAmount":0.0,"CallWonCount":1,"CallWonAmount":1.31,"CallLostCount":1,"CallLostAmount":1.08,"LostCount":1,"LostAmount":1.08},"QQ":{"DealtCount":1,"WonCount":0,"WonAmount":0.0,"ShoveWonCount":0,"ShoveWonAmount":0.0,"ShoveLostCount":0,"ShoveLostAmount":0.0,"CallWonCount":0,"CallWonAmount":0.0,"CallLostCount":1,"CallLostAmount":-0.05,"LostCount":1,"LostAmount":-0.05},"AJ":{"DealtCount":2,"WonCount":1,"WonAmount":1.07,"ShoveWonCount":0,"ShoveWonAmount":0.0,"ShoveLostCount":0,"ShoveLostAmount":0.0,"CallWonCount":1,"CallWonAmount":1.07,"CallLostCount":1,"CallLostAmount":0.55,"LostCount":1,"LostAmount":0.55},"AT":{"DealtCount":1,"WonCount":1,"WonAmount":-0.03,"ShoveWonCount":0,"ShoveWonAmount":0.0,"ShoveLostCount":0,"ShoveLostAmount":0.0,"CallWonCount":1,"CallWonAmount":-0.03,"CallLostCount":0,"CallLostAmount":0.0,"LostCount":0,"LostAmount":0.0},"A9":{"DealtCount":1,"WonCount":0,"WonAmount":0.0,"ShoveWonCount":0,"ShoveWonAmount":0.0,"ShoveLostCount":0,"ShoveLostAmount":0.0,"CallWonCount":0,"CallWonAmount":0.0,"CallLostCount":1,"CallLostAmount":0.08,"LostCount":1,"LostAmount":0.08},"A6":{"DealtCount":1,"WonCount":0,"WonAmount":0.0,"ShoveWonCount":0,"ShoveWonAmount":0.0,"ShoveLostCount":0,"ShoveLostAmount":0.0,"CallWonCount":0,"CallWonAmount":0.0,"CallLostCount":1,"CallLostAmount":0.23,"LostCount":1,"LostAmount":0.23},"KT":{"DealtCount":1,"WonCount":1,"WonAmount":-0.76,"ShoveWonCount":0,"ShoveWonAmount":0.0,"ShoveLostCount":0,"ShoveLostAmount":0.0,"CallWonCount":1,"CallWonAmount":-0.76,"CallLostCount":0,"CallLostAmount":0.0,"LostCount":0,"LostAmount":0.0},"Q8":{"DealtCount":1,"WonCount":1,"WonAmount":1.68,"ShoveWonCount":0,"ShoveWonAmount":0.0,"ShoveLostCount":0,"ShoveLostAmount":0.0,"CallWonCount":1,"CallWonAmount":1.68,"CallLostCount":0,"CallLostAmount":0.0,"LostCount":0,"LostAmount":0.0},"99":{"DealtCount":1,"WonCount":1,"WonAmount":-0.09,"ShoveWonCount":0,"ShoveWonAmount":0.0,"ShoveLostCount":0,"ShoveLostAmount":0.0,"CallWonCount":1,"CallWonAmount":-0.09,"CallLostCount":0,"CallLostAmount":0.0,"LostCount":0,"LostAmount":0.0},"88":{"DealtCount":1,"WonCount":1,"WonAmount":1.87,"ShoveWonCount":0,"ShoveWonAmount":0.0,"ShoveLostCount":0,"ShoveLostAmount":0.0,"CallWonCount":1,"CallWonAmount":1.87,"CallLostCount":0,"CallLostAmount":0.0,"LostCount":0,"LostAmount":0.0},"??":{"DealtCount":0,"WonCount":0,"WonAmount":0.0,"ShoveWonCount":0,"ShoveWonAmount":0.0,"ShoveLostCount":0,"ShoveLostAmount":0.0,"CallWonCount":0,"CallWonAmount":0.0,"CallLostCount":0,"CallLostAmount":0.0,"LostCount":0,"LostAmount":0.0}}},"IsMe":false,"ShoveAllInCount":2,"CallAllInCount":12}