{"TotalHands":130,"HandsPlayed":44,"HandsWon":18,"Bank":0.08,"BankMin":-0.79,"BankMax":1.15,"RakePaid":0.21,"Name":"Swaz85","HandsLost":0,"TotalLostAmount":2.57,"TotalWinAmount":2.96,"ShoveAllInWin":1.00,"ShoveAllInLoss":0.00,"ShoveAllInWinCount":1,"ShoveAllInLostCount":0,"CallAllInWin":0.0,"CallAllInLoss":0.0,"CallAllInWinCount":0,"CallAllInLostCount":0,"PFRCount":13,"VPIPCount":43,"WinVsMe":0.165,"PlayedTheyWonCount":3,"PlayedIWonCount":3,"PostFlopRaiseCount":2,"PostFlopBetCount":17,"PostFlopCallCount":10,"WentToShowDownCount":6,"WentToShowDownAndWonCount":4,"FoldedToAllIn":4,"PlayersFirstFoundDate":"2021-09-08T00:00:00","CashOutGain":0.0,"CallRaisedFirstIn":{"CallRaisedFirstInCounts":{"0.02":{"HoleCards":"A2,T6s","RFIBet":0.02},"0.03":{"HoleCards":"QJ","RFIBet":0.03},"0.04":{"HoleCards":"A9,A8,A6s","RFIBet":0.04}}},"RaisedFirstIn":{"RaisedFirstIn":{"0.02":{"HoleCards":"A6s","RFIBet":0.02}}},"HandMonitor":{"handMonitorCounts":{"AK":{"DealtCount":0,"HitCount":0,"FlopHitCount":0,"TurnHitCount":0,"RiverHitCount":0,"WonCount":0,"WonAmount":0.0,"LostCount":0,"LostAmount":0.0,"NotPlayedHitCount":0,"NotPlayedNotHitCount":0},"AA":{"DealtCount":0,"HitCount":0,"FlopHitCount":0,"TurnHitCount":0,"RiverHitCount":0,"WonCount":0,"WonAmount":0.0,"LostCount":0,"LostAmount":0.0,"NotPlayedHitCount":0,"NotPlayedNotHitCount":0},"KK":{"DealtCount":0,"HitCount":0,"FlopHitCount":0,"TurnHitCount":0,"RiverHitCount":0,"WonCount":0,"WonAmount":0.0,"LostCount":0,"LostAmount":0.0,"NotPlayedHitCount":0,"NotPlayedNotHitCount":0},"QQ":{"DealtCount":0,"HitCount":0,"FlopHitCount":0,"TurnHitCount":0,"RiverHitCount":0,"WonCount":0,"WonAmount":0.0,"LostCount":0,"LostAmount":0.0,"NotPlayedHitCount":0,"NotPlayedNotHitCount":0},"JJ":{"DealtCount":0,"HitCount":0,"FlopHitCount":0,"TurnHitCount":0,"RiverHitCount":0,"WonCount":0,"WonAmount":0.0,"LostCount":0,"LostAmount":0.0,"NotPlayedHitCount":0,"NotPlayedNotHitCount":0},"TT":{"DealtCount":0,"HitCount":0,"FlopHitCount":0,"TurnHitCount":0,"RiverHitCount":0,"WonCount":0,"WonAmount":0.0,"LostCount":0,"LostAmount":0.0,"NotPlayedHitCount":0,"NotPlayedNotHitCount":0},"99":{"DealtCount":0,"HitCount":0,"FlopHitCount":0,"TurnHitCount":0,"RiverHitCount":0,"WonCount":0,"WonAmount":0.0,"LostCount":0,"LostAmount":0.0,"NotPlayedHitCount":0,"NotPlayedNotHitCount":0},"88":{"DealtCount":0,"HitCount":0,"FlopHitCount":0,"TurnHitCount":0,"RiverHitCount":0,"WonCount":0,"WonAmount":0.0,"LostCount":0,"LostAmount":0.0,"NotPlayedHitCount":0,"NotPlayedNotHitCount":0},"77":{"DealtCount":0,"HitCount":0,"FlopHitCount":0,"TurnHitCount":0,"RiverHitCount":0,"WonCount":0,"WonAmount":0.0,"LostCount":0,"LostAmount":0.0,"NotPlayedHitCount":0,"NotPlayedNotHitCount":0},"66":{"DealtCount":0,"HitCount":0,"FlopHitCount":0,"TurnHitCount":0,"RiverHitCount":0,"WonCount":0,"WonAmount":0.0,"LostCount":0,"LostAmount":0.0,"NotPlayedHitCount":0,"NotPlayedNotHitCount":0},"55":{"DealtCount":0,"HitCount":0,"FlopHitCount":0,"TurnHitCount":0,"RiverHitCount":0,"WonCount":0,"WonAmount":0.0,"LostCount":0,"LostAmount":0.0,"NotPlayedHitCount":0,"NotPlayedNotHitCount":0},"44":{"DealtCount":0,"HitCount":0,"FlopHitCount":0,"TurnHitCount":0,"RiverHitCount":0,"WonCount":0,"WonAmount":0.0,"LostCount":0,"LostAmount":0.0,"NotPlayedHitCount":0,"NotPlayedNotHitCount":0},"33":{"DealtCount":0,"HitCount":0,"FlopHitCount":0,"TurnHitCount":0,"RiverHitCount":0,"WonCount":0,"WonAmount":0.0,"LostCount":0,"LostAmount":0.0,"NotPlayedHitCount":0,"NotPlayedNotHitCount":0},"22":{"DealtCount":0,"HitCount":0,"FlopHitCount":0,"TurnHitCount":0,"RiverHitCount":0,"WonCount":0,"WonAmount":0.0,"LostCount":0,"LostAmount":0.0,"NotPlayedHitCount":0,"NotPlayedNotHitCount":0}}},"BankByHand":{},"StartingHands":{"StartingHand":[[0,0,0,0,0,1,1,0,0,0,0,0,1],[0,0,0,0,0,0,0,0,0,0,0,0,0],[0,0,0,1,0,0,0,0,0,0,0,0,0],[0,0,0,0,0,0,0,0,0,0,0,0,0],[0,0,0,0,0,0,0,0,0,0,0,0,0],[0,0,0,0,0,0,0,0,0,0,0,0,0],[0,0,0,0,0,0,0,0,0,0,0,0,0],[0,0,0,0,0,0,0,0,0,0,0,0,0],[1,0,0,0,1,0,0,0,0,0,0,0,0],[0,0,0,0,0,0,0,0,0,0,0,0,0],[0,0,0,0,0,0,0,0,0,0,0,0,0],[0,0,0,0,0,0,0,0,0,0,0,0,0],[0,0,0,0,0,0,0,0,0,0,0,0,0]]},"StartingHandsByPosition":{"StartingHandByPosition":{"UTG":[[0,0,0,0,0,0,0,0,0,0,0,0,0],[0,0,0,0,0,0,0,0,0,0,0,0,0],[0,0,0,0,0,0,0,0,0,0,0,0,0],[0,0,0,0,0,0,0,0,0,0,0,0,0],[0,0,0,0,0,0,0,0,0,0,0,0,0],[0,0,0,0,0,0,0,0,0,0,0,0,0],[0,0,0,0,0,0,0,0,0,0,0,0,0],[0,0,0,0,0,0,0,0,0,0,0,0,0],[0,0,0,0,0,0,0,0,0,0,0,0,0],[0,0,0,0,0,0,0,0,0,0,0,0,0],[0,0,0,0,0,0,0,0,0,0,0,0,0],[0,0,0,0,0,0,0,0,0,0,0,0,0],[0,0,0,0,0,0,0,0,0,0,0,0,0]],"UTG1":[[0,0,0,0,0,0,0,0,0,0,0,0,0],[0,0,0,0,0,0,0,0,0,0,0,0,0],[0,0,0,0,0,0,0,0,0,0,0,0,0],[0,0,0,0,0,0,0,0,0,0,0,0,0],[0,0,0,0,0,0,0,0,0,0,0,0,0],[0,0,0,0,0,0,0,0,0,0,0,0,0],[0,0,0,0,0,0,0,0,0,0,0,0,0],[0,0,0,0,0,0,0,0,0,0,0,0,0],[1,0,0,0,0,0,0,0,0,0,0,0,0],[0,0,0,0,0,0,0,0,0,0,0,0,0],[0,0,0,0,0,0,0,0,0,0,0,0,0],[0,0,0,0,0,0,0,0,0,0,0,0,0],[0,0,0,0,0,0,0,0,0,0,0,0,0]],"UTG2":[[0,0,0,0,0,0,0,0,0,0,0,0,0],[0,0,0,0,0,0,0,0,0,0,0,0,0],[0,0,0,0,0,0,0,0,0,0,0,0,0],[0,0,0,0,0,0,0,0,0,0,0,0,0],[0,0,0,0,0,0,0,0,0,0,0,0,0],[0,0,0,0,0,0,0,0,0,0,0,0,0],[0,0,0,0,0,0,0,0,0,0,0,0,0],[0,0,0,0,0,0,0,0,0,0,0,0,0],[0,0,0,0,0,0,0,0,0,0,0,0,0],[0,0,0,0,0,0,0,0,0,0,0,0,0],[0,0,0,0,0,0,0,0,0,0,0,0,0],[0,0,0,0,0,0,0,0,0,0,0,0,0],[0,0,0,0,0,0,0,0,0,0,0,0,0]],"LJ":[[0,0,0,0,0,0,0,0,0,0,0,0,1],[0,0,0,0,0,0,0,0,0,0,0,0,0],[0,0,0,0,0,0,0,0,0,0,0,0,0],[0,0,0,0,0,0,0,0,0,0,0,0,0],[0,0,0,0,0,0,0,0,0,0,0,0,0],[0,0,0,0,0,0,0,0,0,0,0,0,0],[0,0,0,0,0,0,0,0,0,0,0,0,0],[0,0,0,0,0,0,0,0,0,0,0,0,0],[0,0,0,0,0,0,0,0,0,0,0,0,0],[0,0,0,0,0,0,0,0,0,0,0,0,0],[0,0,0,0,0,0,0,0,0,0,0,0,0],[0,0,0,0,0,0,0,0,0,0,0,0,0],[0,0,0,0,0,0,0,0,0,0,0,0,0]],"HJ":[[0,0,0,0,0,0,0,0,0,0,0,0,0],[0,0,0,0,0,0,0,0,0,0,0,0,0],[0,0,0,0,0,0,0,0,0,0,0,0,0],[0,0,0,0,0,0,0,0,0,0,0,0,0],[0,0,0,0,0,0,0,0,0,0,0,0,0],[0,0,0,0,0,0,0,0,0,0,0,0,0],[0,0,0,0,0,0,0,0,0,0,0,0,0],[0,0,0,0,0,0,0,0,0,0,0,0,0],[0,0,0,0,0,0,0,0,0,0,0,0,0],[0,0,0,0,0,0,0,0,0,0,0,0,0],[0,0,0,0,0,0,0,0,0,0,0,0,0],[0,0,0,0,0,0,0,0,0,0,0,0,0],[0,0,0,0,0,0,0,0,0,0,0,0,0]],"CO":[[0,0,0,0,0,1,0,0,0,0,0,0,0],[0,0,0,0,0,0,0,0,0,0,0,0,0],[0,0,0,0,0,0,0,0,0,0,0,0,0],[0,0,0,0,0,0,0,0,0,0,0,0,0],[0,0,0,0,0,0,0,0,0,0,0,0,0],[0,0,0,0,0,0,0,0,0,0,0,0,0],[0,0,0,0,0,0,0,0,0,0,0,0,0],[0,0,0,0,0,0,0,0,0,0,0,0,0],[0,0,0,0,0,0,0,0,0,0,0,0,0],[0,0,0,0,0,0,0,0,0,0,0,0,0],[0,0,0,0,0,0,0,0,0,0,0,0,0],[0,0,0,0,0,0,0,0,0,0,0,0,0],[0,0,0,0,0,0,0,0,0,0,0,0,0]],"Button":[[0,0,0,0,0,0,0,0,0,0,0,0,0],[0,0,0,0,0,0,0,0,0,0,0,0,0],[0,0,0,0,0,0,0,0,0,0,0,0,0],[0,0,0,0,0,0,0,0,0,0,0,0,0],[0,0,0,0,0,0,0,0,0,0,0,0,0],[0,0,0,0,0,0,0,0,0,0,0,0,0],[0,0,0,0,0,0,0,0,0,0,0,0,0],[0,0,0,0,0,0,0,0,0,0,0,0,0],[0,0,0,0,0,0,0,0,0,0,0,0,0],[0,0,0,0,0,0,0,0,0,0,0,0,0],[0,0,0,0,0,0,0,0,0,0,0,0,0],[0,0,0,0,0,0,0,0,0,0,0,0,0],[0,0,0,0,0,0,0,0,0,0,0,0,0]],"SB":[[0,0,0,0,0,0,0,0,0,0,0,0,0],[0,0,0,0,0,0,0,0,0,0,0,0,0],[0,0,0,1,0,0,0,0,0,0,0,0,0],[0,0,0,0,0,0,0,0,0,0,0,0,0],[0,0,0,0,0,0,0,0,0,0,0,0,0],[0,0,0,0,0,0,0,0,0,0,0,0,0],[0,0,0,0,0,0,0,0,0,0,0,0,0],[0,0,0,0,0,0,0,0,0,0,0,0,0],[0,0,0,0,0,0,0,0,0,0,0,0,0],[0,0,0,0,0,0,0,0,0,0,0,0,0],[0,0,0,0,0,0,0,0,0,0,0,0,0],[0,0,0,0,0,0,0,0,0,0,0,0,0],[0,0,0,0,0,0,0,0,0,0,0,0,0]],"BB":[[0,0,0,0,0,0,1,0,0,0,0,0,0],[0,0,0,0,0,0,0,0,0,0,0,0,0],[0,0,0,0,0,0,0,0,0,0,0,0,0],[0,0,0,0,0,0,0,0,0,0,0,0,0],[0,0,0,0,0,0,0,0,0,0,0,0,0],[0,0,0,0,0,0,0,0,0,0,0,0,0],[0,0,0,0,0,0,0,0,0,0,0,0,0],[0,0,0,0,0,0,0,0,0,0,0,0,0],[0,0,0,0,1,0,0,0,0,0,0,0,0],[0,0,0,0,0,0,0,0,0,0,0,0,0],[0,0,0,0,0,0,0,0,0,0,0,0,0],[0,0,0,0,0,0,0,0,0,0,0,0,0],[0,0,0,0,0,0,0,0,0,0,0,0,0]]}},"BankNetByHand":{"0":0.0,"229682198750":-0.02,"229682202633":0.07,"229682206211":-0.06,"229682211197":-0.01,"229682213156":0.0,"229682216687":0.0,"229682220058":0.0,"229682223883":0.12,"229682229556":0.0,"229682233401":-0.06,"229682237910":0.21,"229682244432":-0.06,"229682251349":-0.01,"229682259565":0.0,"229682261972":0.0,"229682265049":0.0,"229682268811":0.0,"229682277286":0.0,"229682282643":-0.17,"229682291423":0.0,"229682297669":-0.02,"229682302153":-0.01,"229682308164":0.0,"229682311861":0.0,"229682315019":0.0,"229682327648":0.0,"229682331776":0.0,"229682337364":-0.04,"229682341449":-0.01,"229813679957":-0.08,"229813685713":0.03,"229813688186":0.0,"229813696190":0.0,"229813736393":-0.02,"229813739392":-0.01,"229813742278":0.0,"229813748167":0.03,"229813755262":0.0,"229813760813":0.0,"229813767937":0.0,"229813771356":0.0,"229813779599":-0.01,"229813783109":0.03,"229813787615":0.0,"229813805853":-0.04,"229813812283":0.0,"229813818757":-0.06,"229813833605":-0.41,"229813844473":0.0,"229813850532":-0.02,"229813855839":-0.01,"229813859484":-0.04,"229813863906":0.0,"229813870713":0.0,"229813874248":0.0,"229813881537":0.0,"229813894159":0.0,"229813903548":-0.02,"229813910675":-0.01,"229813914760":0.0,"229813918659":0.0,"229813925501":-0.06,"229813933048":-0.02,"229813939259":0.08,"229813945568":0.0,"229813953838":-0.02,"229813964754":0.25,"229813974249":0.0,"229813979709":0.0,"229813987328":0.0,"229813989685":0.20,"229814005968":0.0,"229814014269":0.0,"229814021931":0.44,"229814029238":-0.01,"229814034259":0.0,"229814041911":0.0,"229814050377":1.00,"229814062556":-0.41,"229814117765":0.08,"229814123061":0.0,"229814131179":0.0,"229814138316":-0.24,"229814148059":0.0,"229814172877":-0.03,"229814178332":0.0,"229814181020":-0.02,"229814186064":-0.06,"229814196565":0.01,"229814199042":-0.01,"229814202909":-0.06,"229814209577":0.0,"229814214946":0.0,"229814221870":0.27,"229814233071":-0.06,"229814238297":-0.02,"229814248447":0.0,"229814257396":-0.05,"229814262793":-0.01,"229814266785":0.0,"229814270919":-0.06,"229814280174":0.0,"229814291330":0.0,"229814302219":0.0,"229814309135":-0.04,"229814316386":0.0,"229814329364":-0.19,"229814337773":-0.01,"229814345971":0.0,"229814353670":0.0,"229814357091":0.0,"229814363044":0.05,"229814366741":-0.09,"229814372215":0.0,"229814378972":-0.02,"229814382976":-0.01,"229814389560":0.0,"229814396672":-0.06,"229814408083":0.0,"229814415513":0.0,"229814422102":0.03,"229814425978":0.0,"229814433454":0.0,"229814435873":0.01,"229814442156":-0.01,"229814448223":-0.11,"229814456839":0.0,"229814461574":0.0,"229814470921":0.05,"229814483009":0.0},"PositionPlayedCount":{"UTG":3,"UTG1":6,"UTG2":9,"LJ":3,"HJ":4,"CO":4,"Button":5,"SB":2,"BB":7},"WinByPositionPlayedCount":{"UTG":2,"UTG1":0,"UTG2":5,"LJ":1,"HJ":2,"CO":2,"Button":2,"SB":1,"BB":3},"Steal":{"FoldedToSteal":8,"TotalStolen":0.09,"wonAmount":{"CO":0.03,"Button":0.06,"SB":0.0},"lostAmount":{"CO":0.0,"Button":0.0,"SB":0.0},"stealPosition":{"CO":1,"Button":2,"SB":0},"unsuccessfulStealPosition":{"CO":0,"Button":0,"SB":0}},"AllIns":{"TotalAllInCount":1,"allInCounts":{"??":{"DealtCount":1,"WonCount":0,"WonAmount":0.0,"ShoveWonCount":1,"ShoveWonAmount":1.00,"ShoveLostCount":0,"ShoveLostAmount":0.0,"CallWonCount":0,"CallWonAmount":0.0,"CallLostCount":0,"CallLostAmount":0.0,"LostCount":0,"LostAmount":0.0}}},"IsMe":false,"ShoveAllInCount":1,"CallAllInCount":0}